{"identif": "7489423A002PB5","surname": "МЕДВЕДЕВ","name": "АРТЕМ","sname": "АНДРЕЕВИЧ","sexCode":21000001,"birthday": "20170622","workPlace": "СОВХОЗ \"БЕРЕСТЬЕ\"","workPosition": "ВОДИТЕЛЬ","docTypeCode":54100005,"citizenshipCode":11200001,"docSery": "I-ЛЮ","docNum": "0480737","docDateIssue": "11.05.2012","docIssueOrganCode":17601006,"expireDate": null,"countryBCode":11200001,"areaB": "БРЕСТСКАЯ ОБЛАСТЬ","regionB": "КОБРИНСКИЙ","typeCityBCode":11100001,"cityB": "МАЛОРИТА","inputOldAddress":true,"areaLCode":11300001,"typeCityLCode":11100009,"cityLCode":11915883,"streetLCode":11400430,"house": "3","korps": "","app": "4","regionLCode":11800003,"intracityRegionCode":1,"typeStreetLCode":11700003,"villageCouncilCode":51,"addressLiveDTO":{"ateObjectNum":511,"ateElementUid":44809,"ateAddrNum":0},"form19_20DTO":{"signAway":false,"dateReg": "11.08.2021","regTypeCode":2,"reasonCode":59601016,"noAddrPuCode":0,"countryPuCode":11200001,"areaPu": "БРЕСТСКАЯ ОБЛАСТЬ","regionPu": "КОБРИНСКИЙ","typeCityPuCode":11100001,"cityPu": "БЕРЕЗА","typeStreetPuCode":null,"streetPu": "","housePu": "","korpsPu": "","appPu": "","datePu": "11.08.2021","termRegCode":0,"term": "","dateRegTill": "01.01.1970","notes": "","maritalStatusCode":0,"isStudent":true,"educationCode":1},"docAppleDate": "11.08.2021","viewCode":10,"sysOrgan":201,"organDocCode":17608354,"sysDocTypeCode":8}